LICENSE
MANIFEST.in
README.rst
requirements.txt
setup.cfg
setup.py
astro_datasets/__init__.py
astro_datasets.egg-info/PKG-INFO
astro_datasets.egg-info/SOURCES.txt
astro_datasets.egg-info/dependency_links.txt
astro_datasets.egg-info/requires.txt
astro_datasets.egg-info/top_level.txt
astro_datasets/images/__init__.py
astro_datasets/images/cmd.py
astro_datasets/images/mirabest.py
astro_datasets/images/mlsst.py
astro_datasets/images/slc.py
astro_datasets/time_series/__init__.py
astro_datasets/time_series/plasticc.py
astro_datasets/time_series/spcc.py
astro_datasets/time_series/util.py