Metadata-Version: 1.2
Name: astro-datasets
Version: 0.0.18
Summary: Astronomy and cosmology tensorflow datasets
Home-page: https://github.com/adammoss/astro_datasets/
Author: Adam Moss
Author-email: adam.moss@nottingham.ac.uk
Maintainer: Adam Moss
Maintainer-email: adam.moss@nottingham.ac.uk
License: MIT
Platform: UNKNOWN
Provides: astro_datasets
